libonvif/__init__.py
libonvif/libonvif.cpython-313-aarch64-linux-gnu.so
libonvif/libxml2.so.16
libonvif-3.2.8.dist-info/METADATA
libonvif-3.2.8.dist-info/WHEEL
libonvif-3.2.8.dist-info/top_level.txt
libonvif-3.2.8.dist-info/RECORD
libonvif-3.2.8.dist-info/licenses/LICENSE
