Metadata-Version: 2.4
Name: libonvif
Version: 3.2.8
Summary: A python module for communicating with onvif cameras
Author: Stephen Rhodes
Author-email: Stephen Rhodes <sr99622@gmail.com>
License-Expression: LGPL-2.1
Project-URL: Homepage, https://github.com/sr99622/libonvif
Project-URL: Bug Tracker, https://github.com/sr99622/libonvif/issues
Classifier: Programming Language :: Python :: 3
Classifier: Operating System :: OS Independent
Requires-Python: >=3.10
License-File: LICENSE
Dynamic: author
Dynamic: license-file
Dynamic: requires-python
